dr_ingest/__init__.py
dr_ingest/normalization.py
dr_ingest/py.typed
dr_ingest/types.py
dr_ingest/cli/__init__.py
dr_ingest/cli/parse_scaling_laws.py
dr_ingest/cli/parse_train.py
dr_ingest/configs/__init__.py
dr_ingest/configs/auth.py
dr_ingest/configs/parsed.py
dr_ingest/configs/paths.py
dr_ingest/datadec/__init__.py
dr_ingest/datadec/datadecide.py
dr_ingest/datadec/recipes.py
dr_ingest/hf/__init__.py
dr_ingest/hf/io.py
dr_ingest/hf/location.py
dr_ingest/metrics_all/__init__.py
dr_ingest/metrics_all/constants.py
dr_ingest/metrics_all/eval_record.py
dr_ingest/metrics_all/load_results.py
dr_ingest/motherduck/__init__.py
dr_ingest/motherduck/connector.py
dr_ingest/pipelines/__init__.py
dr_ingest/pipelines/dd_results.py
dr_ingest/pipelines/dd_scaling_laws.py
dr_ingest/qa/__init__.py
dr_ingest/qa/extraction.py
dr_ingest/qa/schemas.py
dr_ingest/qa/transform.py
dr_ingest/utils/__init__.py
dr_ingest/utils/display.py
dr_ingest/utils/io.py
dr_ingest/utils/pandas.py
dr_ingest/wandb/__init__.py
dr_ingest/wandb/classifier.py
dr_ingest/wandb/config.py
dr_ingest/wandb/constants.py
dr_ingest/wandb/hooks.py
dr_ingest/wandb/hydration.py
dr_ingest/wandb/metrics.py
dr_ingest/wandb/normalization_pipeline.py
dr_ingest/wandb/pattern_builders.py
dr_ingest/wandb/patterns.py
dr_ingest/wandb/postprocess.py
dr_ingest/wandb/processing_context.py
dr_ingest/wandb/summary.py
dr_ingest/wandb/tokens.py
dr_ingest-0.1.2.dist-info/METADATA
dr_ingest-0.1.2.dist-info/WHEEL
dr_ingest-0.1.2.dist-info/entry_points.txt
dr_ingest-0.1.2.dist-info/RECORD
