Metadata-Version: 2.4
Name: dr-ingest
Version: 0.1.2
Summary: Helpers for ingesting data.
Author-email: Danielle Rothermel <danielle.rothermel@gmail.com>
Requires-Python: >=3.12
Requires-Dist: argparse>=1.4.0
Requires-Dist: attrs>=25.4.0
Requires-Dist: dotenv>=0.9.9
Requires-Dist: dr-wandb==0.1.2
Requires-Dist: duckdb==1.4.1
Requires-Dist: fastparquet>=2024.11.0
Requires-Dist: huggingface-hub>=1.1.2
Requires-Dist: marimo[sql]==0.17.7
Requires-Dist: more-itertools>=10.8.0
Requires-Dist: pandas>=2.3.3
Requires-Dist: polars>=1.35.2
Requires-Dist: pydantic>=2.12.4
Requires-Dist: pytest>=9.0.1
Requires-Dist: srsly>=2.5.1
Requires-Dist: typer>=0.20.0
